apg_interceptors/__init__.py
apg_interceptors/response_interceptor.py
py_lambda_utils-0.0.3.dist-info/licenses/LICENSE
py_lambda_utils-0.0.3.dist-info/METADATA
py_lambda_utils-0.0.3.dist-info/WHEEL
py_lambda_utils-0.0.3.dist-info/top_level.txt
py_lambda_utils-0.0.3.dist-info/RECORD
