Metadata-Version: 2.4
Name: py-lambda-utils
Version: 0.0.3
Summary: Package for blind panda lambda layers.
Author-email: Ignacio Rondan <ignacio.ezequiel.rondan@gmail.com>
License-Expression: MIT
Project-URL: Homepage, https://github.com/the-blind-panda/py-lambda-utils
Project-URL: Issues, https://github.com/the-blind-panda/py-lambda-utils/issues
Classifier: Programming Language :: Python :: 3
Classifier: Operating System :: OS Independent
Requires-Python: >=3.13
License-File: LICENSE
Dynamic: license-file
